homie_spec/__init__.py
homie_spec/devices.py
homie_spec/messages.py
homie_spec/nodes.py
homie_spec/properties.py
homie_spec/py.typed
homie_spec-0.4.1.dist-info/LICENSE
homie_spec-0.4.1.dist-info/WHEEL
homie_spec-0.4.1.dist-info/METADATA
homie_spec-0.4.1.dist-info/RECORD
