Metadata-Version: 2.1
Name: homie-spec
Version: 0.4.1
Summary: homie-spec is a Python library that handles the v4 Homie Convention
Home-page: https://qu4tro.github.io/homie-spec/
License: MIT
Keywords: homie,mqtt
Author: Xavier Francisco
Author-email: xavier.n.francisco@gmail.com
Requires-Python: >=3.6,<4.0
Classifier: License :: OSI Approved :: MIT License
Classifier: Programming Language :: Python :: 3
Classifier: Programming Language :: Python :: 3.6
Classifier: Programming Language :: Python :: 3.7
Classifier: Programming Language :: Python :: 3.8
Project-URL: Documentation, https://qu4tro.github.io/homie-spec/
Project-URL: Repository, https://github.com/Qu4tro/homie-spec/
